{
  "id": "group-8",
  "title": "Acciones básicas · Useful verbs and descriptions",
  "focus": "High-frequency A1 verbs, simple adjectives and phrases for describing daily needs and actions.",
  "words": [
    {
      "lemma": "necesidad",
      "pos": "noun",
      "gender": "f",
      "translation_en": "need",
      "tag": "Abstract",
      "example": "Tengo una necesidad concreta: practicar cada día.",
      "example_en": "I have a specific need: to practise every day."
    },
    {
      "lemma": "deseo",
      "pos": "noun",
      "gender": "m",
      "translation_en": "wish; desire",
      "tag": "Feelings",
      "example": "Mi deseo es hablar español con más confianza.",
      "example_en": "My wish is to speak Spanish with more confidence."
    },
    {
      "lemma": "noche",
      "pos": "noun",
      "gender": "f",
      "translation_en": "night",
      "tag": "Opinion",
      "example": "Marco la noche en el calendario.",
      "example_en": "I mark the night on the calendar."
    },
    {
      "lemma": "preferencia",
      "pos": "noun",
      "gender": "f",
      "translation_en": "preference",
      "tag": "Opinion",
      "example": "Mi preferencia es estudiar por la mañana.",
      "example_en": "My preference is to study in the morning."
    },
    {
      "lemma": "mediodía",
      "pos": "noun",
      "gender": "m",
      "translation_en": "midday",
      "tag": "Opinion",
      "example": "Marco el mediodía en el calendario.",
      "example_en": "I mark the midday on the calendar."
    },
    {
      "lemma": "madrugada",
      "pos": "noun",
      "gender": "f",
      "translation_en": "early morning",
      "tag": "General",
      "example": "Marco la madrugada en el calendario.",
      "example_en": "I mark the early morning on the calendar."
    },
    {
      "lemma": "primavera",
      "pos": "noun",
      "gender": "f",
      "translation_en": "spring",
      "tag": "Feelings",
      "example": "Marco la primavera en el calendario.",
      "example_en": "I mark the spring on the calendar."
    },
    {
      "lemma": "verano",
      "pos": "noun",
      "gender": "m",
      "translation_en": "summer",
      "tag": "Time",
      "example": "Marco el verano en el calendario.",
      "example_en": "I mark the summer on the calendar."
    },
    {
      "lemma": "otoño",
      "pos": "noun",
      "gender": "m",
      "translation_en": "autumn",
      "tag": "Time",
      "example": "Marco el otoño en el calendario.",
      "example_en": "I mark the autumn on the calendar."
    },
    {
      "lemma": "invierno",
      "pos": "noun",
      "gender": "m",
      "translation_en": "winter",
      "tag": "Routines",
      "example": "Marco el invierno en el calendario.",
      "example_en": "I mark the winter on the calendar."
    },
    {
      "lemma": "quiosco",
      "pos": "noun",
      "gender": "m",
      "translation_en": "kiosk",
      "tag": "Routines",
      "example": "El quiosco está cerca del centro.",
      "example_en": "The kiosk is near the centre."
    },
    {
      "lemma": "cafetería",
      "pos": "noun",
      "gender": "f",
      "translation_en": "café",
      "tag": "Work",
      "example": "La cafetería está cerca del centro.",
      "example_en": "The café is near the centre."
    },
    {
      "lemma": "museo",
      "pos": "noun",
      "gender": "m",
      "translation_en": "museum",
      "tag": "Abstract",
      "example": "El museo está cerca del centro.",
      "example_en": "The museum is near the centre."
    },
    {
      "lemma": "piscina",
      "pos": "noun",
      "gender": "f",
      "translation_en": "swimming pool",
      "tag": "Communication",
      "example": "La piscina está cerca del centro.",
      "example_en": "The swimming pool is near the centre."
    },
    {
      "lemma": "gimnasio",
      "pos": "noun",
      "gender": "m",
      "translation_en": "gym",
      "tag": "Communication",
      "example": "El gimnasio está cerca del centro.",
      "example_en": "The gym is near the centre."
    },
    {
      "lemma": "colegio",
      "pos": "noun",
      "gender": "m",
      "translation_en": "school",
      "tag": "Communication",
      "example": "El colegio está cerca del centro.",
      "example_en": "The school is near the centre."
    },
    {
      "lemma": "instituto",
      "pos": "noun",
      "gender": "m",
      "translation_en": "secondary school",
      "tag": "Communication",
      "example": "El instituto está cerca del centro.",
      "example_en": "The secondary school is near the centre."
    },
    {
      "lemma": "universidad",
      "pos": "noun",
      "gender": "f",
      "translation_en": "university",
      "tag": "Communication",
      "example": "La universidad está cerca del centro.",
      "example_en": "The university is near the centre."
    },
    {
      "lemma": "fábrica",
      "pos": "noun",
      "gender": "f",
      "translation_en": "factory",
      "tag": "City",
      "example": "La fábrica está cerca del centro.",
      "example_en": "The factory is near the centre."
    },
    {
      "lemma": "silencio",
      "pos": "noun",
      "gender": "m",
      "translation_en": "silence",
      "tag": "Communication",
      "example": "Guardo silencio durante la explicación.",
      "example_en": "I keep quiet during the explanation."
    },
    {
      "lemma": "fila",
      "pos": "noun",
      "gender": "f",
      "translation_en": "line, queue",
      "tag": "Home",
      "example": "Dejé la fila junto a la puerta.",
      "example_en": "I left the line, queue by the door."
    },
    {
      "lemma": "vendedor",
      "pos": "noun",
      "gender": "m",
      "translation_en": "salesperson",
      "tag": "Home",
      "example": "Dejé el vendedor junto a la puerta.",
      "example_en": "I left the salesperson by the door."
    },
    {
      "lemma": "compra",
      "pos": "noun",
      "gender": "f",
      "translation_en": "purchase",
      "tag": "Weather",
      "example": "Hoy hablamos de la compra en clase.",
      "example_en": "Today we talk about the purchase in class."
    },
    {
      "lemma": "venta",
      "pos": "noun",
      "gender": "f",
      "translation_en": "sale",
      "tag": "Food & drink",
      "example": "La venta empieza a las diez.",
      "example_en": "The sale starts at ten."
    },
    {
      "lemma": "carné",
      "pos": "noun",
      "gender": "m",
      "translation_en": "ID card, licence",
      "tag": "Food & drink",
      "example": "Puse el carné en la mesa para la cena.",
      "example_en": "I put the ID card, licence on the table for dinner."
    },
    {
      "lemma": "plano",
      "pos": "noun",
      "gender": "m",
      "translation_en": "map, plan",
      "tag": "Routines",
      "example": "Uso el plano en una frase diaria.",
      "example_en": "I use the map, plan in an everyday sentence."
    },
    {
      "lemma": "folleto",
      "pos": "noun",
      "gender": "m",
      "translation_en": "leaflet",
      "tag": "Leisure",
      "example": "Uso el folleto en una frase diaria.",
      "example_en": "I use the leaflet in an everyday sentence."
    },
    {
      "lemma": "vuelo",
      "pos": "noun",
      "gender": "m",
      "translation_en": "flight",
      "tag": "Social",
      "example": "Veo el vuelo en la estación.",
      "example_en": "I see the flight at the station."
    },
    {
      "lemma": "tranvía",
      "pos": "noun",
      "gender": "m",
      "translation_en": "tram",
      "tag": "Communication",
      "example": "Veo el tranvía en la estación.",
      "example_en": "I see the tram at the station."
    },
    {
      "lemma": "pulsera",
      "pos": "noun",
      "gender": "f",
      "translation_en": "bracelet",
      "tag": "Communication",
      "example": "Llevo la pulsera cuando salgo de casa.",
      "example_en": "I take the bracelet when I leave home."
    },
    {
      "lemma": "collar",
      "pos": "noun",
      "gender": "m",
      "translation_en": "necklace",
      "tag": "Shopping",
      "example": "Llevo el collar cuando salgo de casa.",
      "example_en": "I take the necklace when I leave home."
    },
    {
      "lemma": "tirita",
      "pos": "noun",
      "gender": "f",
      "translation_en": "plaster, bandage",
      "tag": "Shopping",
      "example": "Llevo la tirita cuando salgo de casa.",
      "example_en": "I take the plaster, bandage when I leave home."
    },
    {
      "lemma": "cuello",
      "pos": "noun",
      "gender": "m",
      "translation_en": "neck",
      "tag": "Food & drink",
      "example": "Me duele el cuello después de correr.",
      "example_en": "My neck hurts after running."
    },
    {
      "lemma": "muñeca",
      "pos": "noun",
      "gender": "f",
      "translation_en": "wrist",
      "tag": "Food & drink",
      "example": "Me duele la muñeca después de correr.",
      "example_en": "My wrist hurts after running."
    },
    {
      "lemma": "uña",
      "pos": "noun",
      "gender": "f",
      "translation_en": "nail",
      "tag": "Food & drink",
      "example": "Me duele la uña después de correr.",
      "example_en": "My nail hurts after running."
    },
    {
      "lemma": "pecho",
      "pos": "noun",
      "gender": "m",
      "translation_en": "chest",
      "tag": "Food & drink",
      "example": "Me duele el pecho después de correr.",
      "example_en": "My chest hurts after running."
    },
    {
      "lemma": "barriga",
      "pos": "noun",
      "gender": "f",
      "translation_en": "belly",
      "tag": "Food & drink",
      "example": "Me duele la barriga después de correr.",
      "example_en": "My belly hurts after running."
    },
    {
      "lemma": "cintura",
      "pos": "noun",
      "gender": "f",
      "translation_en": "waist",
      "tag": "Food & drink",
      "example": "Me duele la cintura después de correr.",
      "example_en": "My waist hurts after running."
    },
    {
      "lemma": "talón",
      "pos": "noun",
      "gender": "m",
      "translation_en": "heel",
      "tag": "Food & drink",
      "example": "Me duele el talón después de correr.",
      "example_en": "My heel hurts after running."
    },
    {
      "lemma": "labio",
      "pos": "noun",
      "gender": "m",
      "translation_en": "lip",
      "tag": "Health",
      "example": "Me duele el labio después de correr.",
      "example_en": "My lip hurts after running."
    },
    {
      "lemma": "acompañar",
      "pos": "verb",
      "translation_en": "accompany",
      "tag": "Social",
      "example": "Intento acompañar con más naturalidad.",
      "example_en": "I try to accompany more naturally."
    },
    {
      "lemma": "saltar",
      "pos": "verb",
      "translation_en": "to jump",
      "tag": "Money",
      "example": "Hoy puedo saltar en una situación real.",
      "example_en": "Today I can jump in a real situation."
    },
    {
      "lemma": "añadir",
      "pos": "verb",
      "translation_en": "add",
      "tag": "Action",
      "example": "Es útil añadir en situaciones reales.",
      "example_en": "It is useful to add in real situations."
    },
    {
      "lemma": "sentar",
      "pos": "verb",
      "translation_en": "to seat",
      "tag": "Technology",
      "example": "Hoy puedo sentar en una situación real.",
      "example_en": "Today I can seat in a real situation."
    },
    {
      "lemma": "silbar",
      "pos": "verb",
      "translation_en": "to whistle",
      "tag": "Education",
      "example": "Hoy puedo silbar en una situación real.",
      "example_en": "Today I can whistle in a real situation."
    },
    {
      "lemma": "telefonear",
      "pos": "verb",
      "translation_en": "to phone",
      "tag": "Home",
      "example": "Hoy puedo telefonear en una situación real.",
      "example_en": "Today I can phone in a real situation."
    },
    {
      "lemma": "zapatear",
      "pos": "verb",
      "translation_en": "to tap one's feet",
      "tag": "Health",
      "example": "Hoy puedo zapatear en una situación real.",
      "example_en": "Today I can tap one's feet in a real situation."
    },
    {
      "lemma": "masticar",
      "pos": "verb",
      "translation_en": "to chew",
      "tag": "Opinion",
      "example": "Hoy puedo masticar en una situación real.",
      "example_en": "Today I can chew in a real situation."
    },
    {
      "lemma": "batir",
      "pos": "verb",
      "translation_en": "to beat, whisk",
      "tag": "Food & drink",
      "example": "Hoy puedo batir en una situación real.",
      "example_en": "Today I can beat, whisk in a real situation."
    },
    {
      "lemma": "rallar",
      "pos": "verb",
      "translation_en": "to grate",
      "tag": "Transport",
      "example": "Hoy puedo rallar en una situación real.",
      "example_en": "Today I can grate in a real situation."
    },
    {
      "lemma": "cansarse",
      "pos": "verb",
      "translation_en": "to get tired",
      "tag": "Home",
      "example": "Puedo cansarme antes de salir.",
      "example_en": "I can get tired before going out."
    },
    {
      "lemma": "caerse",
      "pos": "verb",
      "translation_en": "to fall",
      "tag": "Action",
      "example": "Puedo caerme antes de salir.",
      "example_en": "I can fall before going out."
    },
    {
      "lemma": "empujar",
      "pos": "verb",
      "translation_en": "to push",
      "tag": "Communication",
      "example": "Hoy puedo empujar en una situación real.",
      "example_en": "Today I can push in a real situation."
    },
    {
      "lemma": "jalar",
      "pos": "verb",
      "translation_en": "to pull",
      "tag": "Health",
      "example": "Hoy puedo jalar en una situación real.",
      "example_en": "Today I can pull in a real situation."
    },
    {
      "lemma": "dibujar",
      "pos": "verb",
      "translation_en": "draw",
      "tag": "Leisure",
      "example": "Es útil dibujar en situaciones reales.",
      "example_en": "It is useful to draw in real situations."
    },
    {
      "lemma": "sujetar",
      "pos": "verb",
      "translation_en": "to hold",
      "tag": "Routines",
      "example": "Hoy puedo sujetar en una situación real.",
      "example_en": "Today I can hold in a real situation."
    },
    {
      "lemma": "soltar",
      "pos": "verb",
      "translation_en": "to let go",
      "tag": "Routines",
      "example": "Hoy puedo soltar en una situación real.",
      "example_en": "Today I can let go in a real situation."
    },
    {
      "lemma": "apretar",
      "pos": "verb",
      "translation_en": "to press, tighten",
      "tag": "Communication",
      "example": "Hoy puedo apretar en una situación real.",
      "example_en": "Today I can press, tighten in a real situation."
    },
    {
      "lemma": "pulsar",
      "pos": "verb",
      "translation_en": "to press",
      "tag": "Communication",
      "example": "Hoy puedo pulsar en una situación real.",
      "example_en": "Today I can press in a real situation."
    },
    {
      "lemma": "enchufar",
      "pos": "verb",
      "translation_en": "to plug in",
      "tag": "Communication",
      "example": "Hoy puedo enchufar en una situación real.",
      "example_en": "Today I can plug in in a real situation."
    },
    {
      "lemma": "desenchufar",
      "pos": "verb",
      "translation_en": "to unplug",
      "tag": "Money",
      "example": "Hoy puedo desenchufar en una situación real.",
      "example_en": "Today I can unplug in a real situation."
    },
    {
      "lemma": "quedarse",
      "pos": "verb",
      "translation_en": "to stay",
      "tag": "Communication",
      "example": "Puedo quedarme antes de salir.",
      "example_en": "I can stay before going out."
    },
    {
      "lemma": "alejarse",
      "pos": "verb",
      "translation_en": "to move away",
      "tag": "Action",
      "example": "Puedo alejarme antes de salir.",
      "example_en": "I can move away before going out."
    },
    {
      "lemma": "torcer",
      "pos": "verb",
      "translation_en": "to turn, twist",
      "tag": "Education",
      "example": "Hoy puedo torcer en una situación real.",
      "example_en": "Today I can turn, twist in a real situation."
    },
    {
      "lemma": "continuar",
      "pos": "verb",
      "translation_en": "to continue",
      "tag": "Communication",
      "example": "Hoy puedo continuar en una situación real.",
      "example_en": "Today I can continue in a real situation."
    },
    {
      "lemma": "montar",
      "pos": "verb",
      "translation_en": "to ride, assemble",
      "tag": "Shopping",
      "example": "Hoy puedo montar en una situación real.",
      "example_en": "Today I can ride, assemble in a real situation."
    },
    {
      "lemma": "pedalear",
      "pos": "verb",
      "translation_en": "to pedal",
      "tag": "Travel",
      "example": "Hoy puedo pedalear en una situación real.",
      "example_en": "Today I can pedal in a real situation."
    },
    {
      "lemma": "patinar",
      "pos": "verb",
      "translation_en": "to skate",
      "tag": "Services",
      "example": "Hoy puedo patinar en una situación real.",
      "example_en": "Today I can skate in a real situation."
    },
    {
      "lemma": "pasear",
      "pos": "verb",
      "translation_en": "to stroll",
      "tag": "Food & drink",
      "example": "Hoy puedo pasear en una situación real.",
      "example_en": "Today I can stroll in a real situation."
    },
    {
      "lemma": "volar",
      "pos": "verb",
      "translation_en": "to fly",
      "tag": "Routines",
      "example": "Hoy puedo volar en una situación real.",
      "example_en": "Today I can fly in a real situation."
    },
    {
      "lemma": "narrar",
      "pos": "verb",
      "translation_en": "to narrate",
      "tag": "Communication",
      "example": "Hoy puedo narrar en una situación real.",
      "example_en": "Today I can narrate in a real situation."
    },
    {
      "lemma": "multiplicar",
      "pos": "verb",
      "translation_en": "to multiply",
      "tag": "Social",
      "example": "Hoy puedo multiplicar en una situación real.",
      "example_en": "Today I can multiply in a real situation."
    },
    {
      "lemma": "dormir",
      "pos": "verb",
      "translation_en": "to sleep",
      "tag": "Social",
      "example": "Hoy puedo dormir en una situación real.",
      "example_en": "Today I can sleep in a real situation."
    },
    {
      "lemma": "soñar",
      "pos": "verb",
      "translation_en": "to dream",
      "tag": "Education",
      "example": "Hoy puedo soñar en una situación real.",
      "example_en": "Today I can dream in a real situation."
    },
    {
      "lemma": "roncar",
      "pos": "verb",
      "translation_en": "to snore",
      "tag": "Education",
      "example": "Hoy puedo roncar en una situación real.",
      "example_en": "Today I can snore in a real situation."
    },
    {
      "lemma": "madrugar",
      "pos": "verb",
      "translation_en": "to get up early",
      "tag": "Travel",
      "example": "Hoy puedo madrugar en una situación real.",
      "example_en": "Today I can get up early in a real situation."
    },
    {
      "lemma": "trasnochar",
      "pos": "verb",
      "translation_en": "to stay up late",
      "tag": "Home",
      "example": "Hoy puedo trasnochar en una situación real.",
      "example_en": "Today I can stay up late in a real situation."
    },
    {
      "lemma": "actual",
      "pos": "adj",
      "translation_en": "current",
      "tag": "Time",
      "example": "La situación es bastante actual.",
      "example_en": "The situation is quite current."
    },
    {
      "lemma": "mayor",
      "pos": "adj",
      "translation_en": "older",
      "tag": "Descriptions",
      "example": "El ejemplo es mayor y fácil de recordar.",
      "example_en": "The example is older and easy to remember."
    },
    {
      "lemma": "básico",
      "pos": "adj",
      "translation_en": "basic",
      "tag": "Education",
      "example": "Me parece una opción básico.",
      "example_en": "It seems like a basic option to me."
    },
    {
      "lemma": "breve",
      "pos": "adj",
      "translation_en": "brief",
      "tag": "Communication",
      "example": "La situación es bastante breve.",
      "example_en": "The situation is quite brief."
    },
    {
      "lemma": "fácil",
      "pos": "adj",
      "translation_en": "easy",
      "tag": "Education",
      "example": "El ejemplo es fácil y fácil de recordar.",
      "example_en": "The example is easy and easy to remember."
    },
    {
      "lemma": "diario",
      "pos": "adj",
      "translation_en": "daily",
      "tag": "Routines",
      "example": "Me parece una opción diario.",
      "example_en": "It seems like a daily option to me."
    },
    {
      "lemma": "difícil",
      "pos": "adj",
      "translation_en": "difficult",
      "tag": "Descriptions",
      "example": "El ejemplo es difícil y fácil de recordar.",
      "example_en": "The example is difficult and easy to remember."
    },
    {
      "lemma": "cómodo",
      "pos": "adj",
      "translation_en": "comfortable",
      "tag": "Education",
      "example": "El ejemplo es cómodo y fácil de recordar.",
      "example_en": "The example is comfortable and easy to remember."
    },
    {
      "lemma": "incómodo",
      "pos": "adj",
      "translation_en": "uncomfortable",
      "tag": "Food & drink",
      "example": "El ejemplo es incómodo y fácil de recordar.",
      "example_en": "The example is uncomfortable and easy to remember."
    },
    {
      "lemma": "libre",
      "pos": "adj",
      "translation_en": "free, available",
      "tag": "People",
      "example": "El ejemplo es libre y fácil de recordar.",
      "example_en": "The example is free, available and easy to remember."
    },
    {
      "lemma": "integral",
      "pos": "adj",
      "translation_en": "wholemeal",
      "tag": "Health",
      "example": "El ejemplo es integral y fácil de recordar.",
      "example_en": "The example is wholemeal and easy to remember."
    },
    {
      "lemma": "desnatado",
      "pos": "adj",
      "translation_en": "skimmed",
      "tag": "Opinion",
      "example": "El ejemplo es desnatado y fácil de recordar.",
      "example_en": "The example is skimmed and easy to remember."
    },
    {
      "lemma": "artificial",
      "pos": "adj",
      "translation_en": "man-made",
      "tag": "Descriptions",
      "example": "El ejemplo es artificial y fácil de recordar.",
      "example_en": "The example is man-made and easy to remember."
    },
    {
      "lemma": "parecido",
      "pos": "adj",
      "translation_en": "similar",
      "tag": "Descriptions",
      "example": "Es un tema parecido para el examen.",
      "example_en": "It is a similar topic for the exam."
    },
    {
      "lemma": "tardío",
      "pos": "adj",
      "translation_en": "late",
      "tag": "Time",
      "example": "El ejemplo es tardío y fácil de recordar.",
      "example_en": "The example is late and easy to remember."
    },
    {
      "lemma": "contento",
      "pos": "adj",
      "translation_en": "happy",
      "tag": "Education",
      "example": "El ejemplo es contento y fácil de recordar.",
      "example_en": "The example is happy and easy to remember."
    },
    {
      "lemma": "despacio",
      "pos": "adv",
      "translation_en": "slowly",
      "tag": "Manner",
      "example": "Lo explico despacio cuando puedo.",
      "example_en": "I explain it slowly when I can."
    },
    {
      "lemma": "deprisa",
      "pos": "adv",
      "translation_en": "quickly",
      "tag": "Time",
      "example": "Hoy estudio deprisa durante diez minutos.",
      "example_en": "Today I study quickly for ten minutes."
    },
    {
      "lemma": "mañana",
      "pos": "adv",
      "translation_en": "tomorrow",
      "tag": "Time",
      "example": "Hoy estudio mañana durante diez minutos.",
      "example_en": "Today I study tomorrow for ten minutes."
    },
    {
      "lemma": "a mi lado",
      "pos": "phrase",
      "translation_en": "by my side",
      "tag": "Place",
      "example": "Mi hermano se sienta a mi lado en clase.",
      "example_en": "My brother sits by my side in class."
    },
    {
      "lemma": "con cuidado",
      "pos": "phrase",
      "translation_en": "carefully",
      "tag": "Manner",
      "example": "Cruza la calle con cuidado.",
      "example_en": "Cross the street carefully."
    },
    {
      "lemma": "de nuevo",
      "pos": "phrase",
      "translation_en": "again",
      "tag": "Action",
      "example": "Repito la frase de nuevo para practicar.",
      "example_en": "I repeat the sentence again to practise."
    },
    {
      "lemma": "en voz alta",
      "pos": "phrase",
      "translation_en": "out loud",
      "tag": "Communication",
      "example": "Leo el diálogo en voz alta.",
      "example_en": "I read the dialogue out loud."
    }
  ]
}
